{"type":"BufferGeometry","uuid":"7B41E640-9CE3-425B-8DB0-E26107758839","data":{"attributes":{"position":{"type":"Float32Array","itemSize":3,"normalized":false,"array":[]},"normal":{"type":"Float32Array","itemSize":3,"normalized":false,"array":[]},"color":{"type":"Float32Array","itemSize":3,"normalized":false,"array":[]},"uv":{"type":"Float32Array","itemSize":2,"normalized":false,"array":[]},"ao":{"type":"Float32Array","itemSize":1,"normalized":false,"array":[]},"blocklight":{"type":"Float32Array","itemSize":1,"normalized":false,"array":[]},"sunlight":{"type":"Float32Array","itemSize":1,"normalized":false,"array":[]}},"groups":[]}}